{   
    "Sample_Solutions": {
        "Use": true,
        "solution": "pos_x_squared"
    },
    "Solution_Name": "custom",
    "Physical_Parameters": {
        "a": 1,
        "b": 1,
        "L": 2,
        "k": 1,
        "g_function": "1-x*(x-2)"
    },
    "Solution_Parameters": {
        "amount_of_x_points": 30,
        "amount_of_t_points": 100,
        "final_t": 1,
        "partial_sum_amount": 10,
        "FPS": 15
    },
    "Numerical_Solution_Parameters": {
        "mu_1": 1,
        "mu_2": 1,
        "delta_x": 0.1,
        "delta_t": 0.004
    }
}